metadata_crawler/__init__.py
metadata_crawler/__init__.pyi
metadata_crawler/__main__.py
metadata_crawler/_helper.abi3.so
metadata_crawler/_helper.pyi
metadata_crawler/_version.py
metadata_crawler/api/__init__.py
metadata_crawler/api/cli.py
metadata_crawler/api/config.py
metadata_crawler/api/drs_config.toml
metadata_crawler/api/index.py
metadata_crawler/api/metadata_stores.py
metadata_crawler/api/mixin/__init__.py
metadata_crawler/api/mixin/lookup_mixin.py
metadata_crawler/api/mixin/lookup_tables.py
metadata_crawler/api/mixin/path_mixin.py
metadata_crawler/api/mixin/template_mixin.py
metadata_crawler/api/storage_backend.py
metadata_crawler/backends/__init__.py
metadata_crawler/backends/intake.py
metadata_crawler/backends/posix.py
metadata_crawler/backends/s3.py
metadata_crawler/backends/swift.py
metadata_crawler/cli.py
metadata_crawler/data_collector.py
metadata_crawler/ingester/__init__.py
metadata_crawler/ingester/mongo.py
metadata_crawler/ingester/solr.py
metadata_crawler/logger.py
metadata_crawler/py.typed
metadata_crawler/run.py
metadata_crawler/utils/__init__.py
metadata_crawler/utils/cftime_utils.py
metadata_crawler-2602.0.0.dist-info/METADATA
metadata_crawler-2602.0.0.dist-info/WHEEL
metadata_crawler-2602.0.0.dist-info/entry_points.txt
metadata_crawler-2602.0.0.dist-info/licenses/LICENSE
metadata_crawler-2602.0.0.dist-info/RECORD
