Metadata-Version: 2.4
Name: metadata-crawler
Version: 2602.0.0
Classifier: Development Status :: 4 - Beta
Classifier: Environment :: Console
Classifier: Intended Audience :: Developers
Classifier: Intended Audience :: Science/Research
Classifier: License :: OSI Approved :: BSD License
Classifier: Operating System :: POSIX :: Linux
Classifier: Programming Language :: Rust
Classifier: Programming Language :: Python :: 3
Classifier: Programming Language :: Python :: 3.11
Classifier: Programming Language :: Python :: 3.12
Classifier: Programming Language :: Python :: 3.13
Classifier: Programming Language :: Python :: 3.14
Requires-Dist: aiohttp
Requires-Dist: appdirs
Requires-Dist: ciso8601
Requires-Dist: fsspec
Requires-Dist: diskcache
Requires-Dist: s3fs
Requires-Dist: jinja2
Requires-Dist: ipython
Requires-Dist: intake
Requires-Dist: intake-xarray
Requires-Dist: intake-esm
Requires-Dist: pandas
Requires-Dist: python-dateutil
Requires-Dist: numpy
Requires-Dist: orjson
Requires-Dist: pyarrow
Requires-Dist: h5netcdf
Requires-Dist: h5py
Requires-Dist: pydantic
Requires-Dist: pyarrow
Requires-Dist: rich
Requires-Dist: rich-argparse
Requires-Dist: rtoml
Requires-Dist: tomlkit
Requires-Dist: typing-extensions
Requires-Dist: zarr
Requires-Dist: xarray
Requires-Dist: httpx
Requires-Dist: uvloop ; sys_platform != 'win32'
Requires-Dist: motor
Requires-Dist: maturin ; extra == 'dev'
Requires-Dist: tox ; extra == 'dev'
Requires-Dist: codespell ; extra == 'doc'
Requires-Dist: blacken-docs ; extra == 'doc'
Requires-Dist: numpydoc ; extra == 'doc'
Requires-Dist: sphinx ; extra == 'doc'
Requires-Dist: sphinxcontrib-github-alt ; extra == 'doc'
Requires-Dist: sphinx-execute-code-python3 ; extra == 'doc'
Requires-Dist: sphinx-copybutton ; extra == 'doc'
Requires-Dist: sphinx-sitemap ; extra == 'doc'
Requires-Dist: sphinx-togglebutton ; extra == 'doc'
Requires-Dist: sphinxext-opengraph[social-cards] ; extra == 'doc'
Requires-Dist: pydata-sphinx-theme ; extra == 'doc'
Requires-Dist: myst-parser ; extra == 'doc'
Requires-Dist: mkdocs ; extra == 'mkdoc'
Requires-Dist: mkdocs-material ; extra == 'mkdoc'
Requires-Dist: mkdocstrings[python] ; extra == 'mkdoc'
Requires-Dist: mkdocs-macros-plugin ; extra == 'mkdoc'
Requires-Dist: mkdocs-minify-plugin ; extra == 'mkdoc'
Requires-Dist: mkdocs-redirects ; extra == 'mkdoc'
Requires-Dist: mike ; extra == 'mkdoc'
Requires-Dist: codespell ; extra == 'tests'
Requires-Dist: pydocstyle ; extra == 'tests'
Requires-Dist: types-appdirs ; extra == 'tests'
Requires-Dist: black ; extra == 'tests'
Requires-Dist: isort ; extra == 'tests'
Requires-Dist: mock ; extra == 'tests'
Requires-Dist: mypy ; extra == 'tests'
Requires-Dist: netcdf4 ; extra == 'tests'
Requires-Dist: pandas ; extra == 'tests'
Requires-Dist: intake-parquet ; extra == 'tests'
Requires-Dist: pytest-asyncio ; extra == 'tests'
Requires-Dist: pytest-cov ; extra == 'tests'
Requires-Dist: pytest-env ; extra == 'tests'
Requires-Dist: requests ; extra == 'tests'
Requires-Dist: pre-commit ; extra == 'tests'
Requires-Dist: toml ; extra == 'tests'
Provides-Extra: dev
Provides-Extra: doc
Provides-Extra: mkdoc
Provides-Extra: tests
License-File: LICENSE
Summary: Crawl, extract and push climate metadata for indexing.
Author-email: "DKRZ, Clint" <freva@dkrz.de>
Requires-Python: >=3.11
Project-URL: Documentation, https://metadata-crawler.readthedocs.io
Project-URL: Home, https://github.com/freva-org/metadata-crawler
Project-URL: Issues, https://github.com/freva-org/metadata-crawler/issues
Project-URL: Source, https://github.com/freva-org/metadata-crawler
